CHANGES.txt
LICENSE.txt
MANIFEST.in
MacInstallation.sh
README.md
UbuntuInstallation.sh
ez_setup.py
setup.py
Bin/DataGenerate_SineWave.py
Bin/Data_CSV.py
Bin/__init__.py
Bin/converter.py
Bin/csvformatter.py
Bin/gen_nyse_dates.py
Bin/investors_report.py
Examples/Validation.py
Examples/Basic/allsyms.csv
Examples/Basic/example-data.csv
Examples/Basic/example-syms.csv
Examples/Basic/numpy-tutorial.py
Examples/Basic/pandas-tutorial.py
Examples/Basic/tutorial1.py
Examples/Basic/tutorial2.py
Examples/Basic/tutorial3.py
Examples/Basic/tutorial3portfolio.csv
Examples/Basic/tutorial4.py
Examples/Basic/tutorial5.py
Examples/Basic/tutorial8.py
Examples/DataAccess/setexample.py
Examples/EventProfiler/SP500port.csv
Examples/EventProfiler/tutorial.py
Examples/FeatureSearch/2008Dow30.txt
Examples/FeatureSearch/2010Dow30.txt
Examples/FeatureSearch/code.py
Examples/FeatureSearch/functions.py
Examples/FeatureSearch/runs.txt
Examples/Features/featuretest.py
Examples/Features/symbols.txt
Examples/KNN/data-classification-prob.csv
Examples/KNN/data-ripple-prob.csv
Examples/KNN/data1.csv
Examples/KNN/data2.csv
QSTK/__init__.py
QSTK/__init__.pyc
QSTK.egg-info/PKG-INFO
QSTK.egg-info/SOURCES.txt
QSTK.egg-info/dependency_links.txt
QSTK.egg-info/namespace_packages.txt
QSTK.egg-info/requires.txt
QSTK.egg-info/top_level.txt
QSTK/QSData/Yahoo/$DJI.csv
QSTK/QSData/Yahoo/$SPX.csv
QSTK/QSData/Yahoo/$VIX.csv
QSTK/QSData/Yahoo/A.csv
QSTK/QSData/Yahoo/AA.csv
QSTK/QSData/Yahoo/AAPL.csv
QSTK/QSData/Yahoo/ABC.csv
QSTK/QSData/Yahoo/ABI.csv
QSTK/QSData/Yahoo/ABKFQ.csv
QSTK/QSData/Yahoo/ABT.csv
QSTK/QSData/Yahoo/ACAS.csv
QSTK/QSData/Yahoo/ACE.csv
QSTK/QSData/Yahoo/ACN.csv
QSTK/QSData/Yahoo/ACS.csv
QSTK/QSData/Yahoo/ADBE.csv
QSTK/QSData/Yahoo/ADI.csv
QSTK/QSData/Yahoo/ADM.csv
QSTK/QSData/Yahoo/ADP.csv
QSTK/QSData/Yahoo/ADSK.csv
QSTK/QSData/Yahoo/AEE.csv
QSTK/QSData/Yahoo/AEP.csv
QSTK/QSData/Yahoo/AES.csv
QSTK/QSData/Yahoo/AET.csv
QSTK/QSData/Yahoo/AFL.csv
QSTK/QSData/Yahoo/AGN.csv
QSTK/QSData/Yahoo/AIG.csv
QSTK/QSData/Yahoo/AIV.csv
QSTK/QSData/Yahoo/AIZ.csv
QSTK/QSData/Yahoo/AKAM.csv
QSTK/QSData/Yahoo/ALL.csv
QSTK/QSData/Yahoo/ALTR.csv
QSTK/QSData/Yahoo/ALXN.csv
