Metadata-Version: 1.1
Name: QSTK
Version: 0.2.7
Summary: QuantSoftware Toolkit
Home-page: https://github.com/QuantSoftware/QuantSoftwareToolkit
Author: Sourabh Bajaj
Author-email: sourabhbajaj90@gmail.com
License: The QuantSoftware ToolKit (QSTK) is released under the New BSD License as follows:
